README.txt
base.cfg
bootstrap.py
buildout.cfg
plone3.cfg
setup.py
docs/HISTORY.txt
docs/INSTALL.txt
docs/LICENSE.GPL
docs/LICENSE.txt
src/example/__init__.py
src/example.blobattype.egg-info/PKG-INFO
src/example.blobattype.egg-info/SOURCES.txt
src/example.blobattype.egg-info/dependency_links.txt
src/example.blobattype.egg-info/entry_points.txt
src/example.blobattype.egg-info/namespace_packages.txt
src/example.blobattype.egg-info/not-zip-safe
src/example.blobattype.egg-info/requires.txt
src/example.blobattype.egg-info/top_level.txt
src/example/blobattype/__init__.py
src/example/blobattype/config.py
src/example/blobattype/configure.zcml
src/example/blobattype/content.py
src/example/blobattype/extender.py
src/example/blobattype/interfaces.py
src/example/blobattype/migrator.py
src/example/blobattype/browser/__init__.py
src/example/blobattype/browser/configure.zcml
src/example/blobattype/browser/migrateblobs.py
src/example/blobattype/profiles/default/factorytool.xml
src/example/blobattype/profiles/default/metadata.xml
src/example/blobattype/profiles/default/rolemap.xml
src/example/blobattype/profiles/default/types.xml
src/example/blobattype/profiles/default/types/ExampleATType.xml
src/example/blobattype/tests/__init__.py
src/example/blobattype/tests/base.py
src/example/blobattype/tests/layer.py
src/example/blobattype/tests/test_integration.py