Metadata-Version: 1.0
Name: example.blobattype
Version: 1.0b1
Summary: Example of migrating an AT-based content type using blob-enabled FileFields.
Home-page: http://pypi.python.org/pypi/example.blobattype
Author: George Gozadinos
Author-email: ggozad@qiweb.net
License: GPL
Keywords: plone blobs archetypes content example
Platform: Any
Classifier: Environment :: Web Environment
Classifier: Framework :: Plone
Classifier: Intended Audience :: Developers
Classifier: License :: OSI Approved :: GNU General Public License (GPL)
Classifier: Operating System :: OS Independent
Classifier: Programming Language :: Python
Classifier: Topic :: Software Development :: Libraries :: Python Modules
